iqtester/__init__.py
iqtester/__main__.py
iqtester/board.py
iqtester/formatter.py
iqtester/game.py
iqtester/session.py
iqtester-0.2.1.dist-info/LICENSE.md
iqtester-0.2.1.dist-info/METADATA
iqtester-0.2.1.dist-info/WHEEL
iqtester-0.2.1.dist-info/entry_points.txt
iqtester-0.2.1.dist-info/top_level.txt
iqtester-0.2.1.dist-info/RECORD
