Metadata-Version: 2.1
Name: iqtester
Version: 0.2.1
Summary: A Python CLI version of the classic brain game IQ Tester
Author-email: Andrew Tracey <act.project.alpha@gmail.com>
License: MIT License        
Project-URL: Homepage, https://github.com/andrewt110216/iq-tester-game
Keywords: iq tester,game,classic game
Classifier: Topic :: Games/Entertainment
Classifier: Topic :: Games/Entertainment :: Puzzle Games
Classifier: Topic :: Games/Entertainment :: Board Games
Classifier: Programming Language :: Python
Classifier: Programming Language :: Python :: 3
Classifier: License :: OSI Approved :: MIT License
Requires-Python: >=3.7
License-File: LICENSE.md
Requires-Dist: colorama
Provides-Extra: dev
Requires-Dist: pytest ; extra == 'dev'
Requires-Dist: flake8 ; extra == 'dev'
